examples/__init__.py
examples/main.py
uttm/__init__.py
uttm/preprocess.py
uttm/refinement.py
uttm/template_matcher.py
uttm-1.0.6.dist-info/LICENSE
uttm-1.0.6.dist-info/METADATA
uttm-1.0.6.dist-info/WHEEL
uttm-1.0.6.dist-info/top_level.txt
uttm-1.0.6.dist-info/RECORD
