Metadata-Version: 2.2
Name: uttm
Version: 1.0.6
Summary: UTTM(Unsupervised-Torch-Template-Matching) is a tool for robust 2D template matching based on torch unsupervised learning.
Author-email: Xiao Zhou <xiao_zhou@roboticplus.com>, czhou <chengzhe_zhou@roboticplus.com>, longxl <xiaoling_long@roboticplus.com>
License: MIT License
Project-URL: Repository, http://gitlab.roboticplus.com:2022/zhouxiao_jojo/unsupervised-torch-template-matching
Project-URL: Documentation, http://gitlab.roboticplus.com:2022/zhouxiao_jojo/unsupervised-torch-template-matching
Project-URL: SampleData, https://drive.google.com/drive/folders/1m9idEbKWOyDbeqHgnHHvbdW2UAv4ANhC
Keywords: Template-Matching,Torch
Classifier: Development Status :: 4 - Beta
Classifier: Intended Audience :: Developers
Classifier: Operating System :: OS Independent
Classifier: Programming Language :: Python :: 3
Classifier: License :: OSI Approved :: MIT License
Requires-Python: >=3.10
License-File: LICENSE
Requires-Dist: numpy
Requires-Dist: scipy
Requires-Dist: torch
Requires-Dist: torchvision
Requires-Dist: opencv-python>4.0
Provides-Extra: example
Requires-Dist: matplotlib; extra == "example"
